nonebot_plugin_templates/__init__.py
nonebot_plugin_templates/template_types.py
nonebot_plugin_templates/templates/cards.html
nonebot_plugin_templates/templates/colorlist.html
nonebot_plugin_templates/templates/grid.html
nonebot_plugin_templates/templates/menus.html
nonebot_plugin_templates/templates/PingFang.ttf
nonebot_plugin_templates/templates_render.py
nonebot_plugin_templates-0.1.6.dist-info/METADATA
nonebot_plugin_templates-0.1.6.dist-info/WHEEL
nonebot_plugin_templates-0.1.6.dist-info/RECORD
