Metadata-Version: 2.1
Name: nonebot-plugin-templates
Version: 0.1.6
Summary: 为nonebot提供一系列jinja2 template模板,方便的生成图片
Author: canxin
Author-email: 1969730106@qq.com
Requires-Python: >=3.8,<4.0
Classifier: Programming Language :: Python :: 3
Classifier: Programming Language :: Python :: 3.8
Classifier: Programming Language :: Python :: 3.9
Classifier: Programming Language :: Python :: 3.10
Classifier: Programming Language :: Python :: 3.11
Requires-Dist: nonebot-plugin-htmlrender (>=0.2.1,<0.3.0)
Requires-Dist: nonebot2 (>=2.0.0,<3.0.0)
